blochsphere/__init__.py
blochsphere/__main__.py
neze_bloch_sphere-0.dist-info/METADATA
neze_bloch_sphere-0.dist-info/RECORD
neze_bloch_sphere-0.dist-info/WHEEL
neze_bloch_sphere-0.dist-info/top_level.txt
