Metadata-Version: 2.1
Name: neze-bloch-sphere
Version: 0
Summary: Bloch sphere simulation
Home-page: UNKNOWN
Author: Clement Durand
Author-email: durand.clement.13@gmail.com
License: UNKNOWN
Platform: UNKNOWN
Classifier: Programming Language :: Python :: 3
Requires-Dist: matplotlib
Requires-Dist: numpy
